settei/__init__.py
settei/base.py
settei/parse_env.py
settei/utils.py
settei/version.py
settei/presets/__init__.py
settei/presets/celery.py
settei/presets/flask.py
settei/presets/logging.py
settei-0.7.3.dist-info/LICENSE
settei-0.7.3.dist-info/METADATA
settei-0.7.3.dist-info/WHEEL
settei-0.7.3.dist-info/top_level.txt
settei-0.7.3.dist-info/RECORD
